tchumyt_pypi/__init__.py
tchumyt_pypi/configs/__init__.py
tchumyt_pypi/configs/logger/__init__.py
tchumyt_pypi/configs/logger/logging-config.json
tchumyt_pypi/tokenizers/__init__.py
tchumyt_pypi/tokenizers/bpe_tokenizer.py
tchumyt_pypi-0.2.1.dist-info/METADATA
tchumyt_pypi-0.2.1.dist-info/WHEEL
tchumyt_pypi-0.2.1.dist-info/RECORD
